abby/__init__.py
abby/compare.py
abby/datasets.py
abby/diagnose.py
abby/utils.py
abby/tests/__init__.py
abby/tests/test_bootstrap.py
abby/tests/test_delta.py
abby/tests/test_multiple.py
abby/tests/test_ttest.py
abby/tests/datasets/click_impression.csv
abby/tests/datasets/click_impression_3_variants.csv
abby/tests/datasets/penguins.csv
abby/tests/datasets/sleeps.csv
abby-0.1.2.dist-info/LICENSE
abby-0.1.2.dist-info/WHEEL
abby-0.1.2.dist-info/METADATA
abby-0.1.2.dist-info/RECORD
